{
  "svgate.md": {
    "modified": 1775337827.0803714,
    "vectors": [
      "svgate.md_0",
      "svgate.md_1",
      "svgate.md_2",
      "svgate.md_3",
      "svgate.md_4",
      "svgate.md_5",
      "svgate.md_6",
      "svgate.md_7"
    ],
    "name": "svgate.md"
  },
  "humo-payment.md": {
    "modified": 1775337705.1241767,
    "vectors": [
      "humo-payment.md_0",
      "humo-payment.md_1",
      "humo-payment.md_2",
      "humo-payment.md_3",
      "humo-payment.md_4",
      "humo-payment.md_5",
      "humo-payment.md_6",
      "humo-payment.md_7",
      "humo-payment.md_8",
      "humo-payment.md_9",
      "humo-payment.md_10"
    ],
    "name": "humo-payment.md"
  },
  "humo-middleware.md": {
    "modified": 1775337803.9873855,
    "vectors": [
      "humo-middleware.md_0",
      "humo-middleware.md_1",
      "humo-middleware.md_2",
      "humo-middleware.md_3",
      "humo-middleware.md_4",
      "humo-middleware.md_5",
      "humo-middleware.md_6",
      "humo-middleware.md_7",
      "humo-middleware.md_8"
    ],
    "name": "humo-middleware.md"
  },
  "customers.md": {
    "modified": 1775337685.2992826,
    "vectors": [
      "customers.md_0",
      "customers.md_1",
      "customers.md_2",
      "customers.md_3",
      "customers.md_4",
      "customers.md_5",
      "customers.md_6",
      "customers.md_7",
      "customers.md_8"
    ],
    "name": "customers.md"
  },
  "bayt-api.md": {
    "modified": 1775337876.2819507,
    "vectors": [
      "bayt-api.md_0",
      "bayt-api.md_1",
      "bayt-api.md_2",
      "bayt-api.md_3",
      "bayt-api.md_4",
      "bayt-api.md_5",
      "bayt-api.md_6",
      "bayt-api.md_7",
      "bayt-api.md_8",
      "bayt-api.md_9"
    ],
    "name": "bayt-api.md"
  },
  "bayt-api-manager.md": {
    "modified": 1775337725.3362536,
    "vectors": [
      "bayt-api-manager.md_0",
      "bayt-api-manager.md_1",
      "bayt-api-manager.md_2",
      "bayt-api-manager.md_3",
      "bayt-api-manager.md_4",
      "bayt-api-manager.md_5",
      "bayt-api-manager.md_6"
    ],
    "name": "bayt-api-manager.md"
  },
  "paynet-manager.md": {
    "modified": 1775337785.3331103,
    "vectors": [
      "paynet-manager.md_0",
      "paynet-manager.md_1",
      "paynet-manager.md_2",
      "paynet-manager.md_3",
      "paynet-manager.md_4",
      "paynet-manager.md_5",
      "paynet-manager.md_6",
      "paynet-manager.md_7",
      "paynet-manager.md_8",
      "paynet-manager.md_9"
    ],
    "name": "paynet-manager.md"
  },
  "currency-manager.md": {
    "modified": 1775337849.7742293,
    "vectors": [
      "currency-manager.md_0",
      "currency-manager.md_1",
      "currency-manager.md_2",
      "currency-manager.md_3",
      "currency-manager.md_4",
      "currency-manager.md_5",
      "currency-manager.md_6",
      "currency-manager.md_7",
      "currency-manager.md_8"
    ],
    "name": "currency-manager.md"
  },
  "iabs.md": {
    "modified": 1775337757.4487054,
    "vectors": [
      "iabs.md_0",
      "iabs.md_1",
      "iabs.md_2",
      "iabs.md_3",
      "iabs.md_4",
      "iabs.md_5",
      "iabs.md_6"
    ],
    "name": "iabs.md"
  },
  "pc-manager.md": {
    "modified": 1775337936.499755,
    "vectors": [
      "pc-manager.md_0",
      "pc-manager.md_1",
      "pc-manager.md_2",
      "pc-manager.md_3",
      "pc-manager.md_4",
      "pc-manager.md_5",
      "pc-manager.md_6",
      "pc-manager.md_7",
      "pc-manager.md_8",
      "pc-manager.md_9",
      "pc-manager.md_10"
    ],
    "name": "pc-manager.md"
  },
  "smsxabar.md": {
    "modified": 1775337860.843412,
    "vectors": [
      "smsxabar.md_0",
      "smsxabar.md_1",
      "smsxabar.md_2",
      "smsxabar.md_3",
      "smsxabar.md_4",
      "smsxabar.md_5",
      "smsxabar.md_6",
      "smsxabar.md_7",
      "smsxabar.md_8"
    ],
    "name": "smsxabar.md"
  },
  "paynet.md": {
    "modified": 1775337904.360646,
    "vectors": [
      "paynet.md_0",
      "paynet.md_1",
      "paynet.md_2",
      "paynet.md_3",
      "paynet.md_4",
      "paynet.md_5",
      "paynet.md_6",
      "paynet.md_7",
      "paynet.md_8",
      "paynet.md_9"
    ],
    "name": "paynet.md"
  },
  "telecom-af.md": {
    "modified": 1775337741.0520952,
    "vectors": [
      "telecom-af.md_0",
      "telecom-af.md_1",
      "telecom-af.md_2",
      "telecom-af.md_3",
      "telecom-af.md_4",
      "telecom-af.md_5",
      "telecom-af.md_6",
      "telecom-af.md_7",
      "telecom-af.md_8"
    ],
    "name": "telecom-af.md"
  },
  "01-structure.md": {
    "modified": 1775331137.710648,
    "vectors": [
      "01-structure.md_0",
      "01-structure.md_1",
      "01-structure.md_2",
      "01-structure.md_3",
      "01-structure.md_4",
      "01-structure.md_5",
      "01-structure.md_6",
      "01-structure.md_7",
      "01-structure.md_8",
      "01-structure.md_9",
      "01-structure.md_10",
      "01-structure.md_11",
      "01-structure.md_12",
      "01-structure.md_13",
      "01-structure.md_14",
      "01-structure.md_15",
      "01-structure.md_16",
      "01-structure.md_17"
    ],
    "name": "01-structure.md"
  },
  "CONVENTIONS.md": {
    "modified": 1775331375.0304453,
    "vectors": [
      "CONVENTIONS.md_0",
      "CONVENTIONS.md_1",
      "CONVENTIONS.md_2",
      "CONVENTIONS.md_3",
      "CONVENTIONS.md_4",
      "CONVENTIONS.md_5",
      "CONVENTIONS.md_6",
      "CONVENTIONS.md_7",
      "CONVENTIONS.md_8",
      "CONVENTIONS.md_9",
      "CONVENTIONS.md_10",
      "CONVENTIONS.md_11",
      "CONVENTIONS.md_12",
      "CONVENTIONS.md_13",
      "CONVENTIONS.md_14",
      "CONVENTIONS.md_15",
      "CONVENTIONS.md_16",
      "CONVENTIONS.md_17",
      "CONVENTIONS.md_18",
      "CONVENTIONS.md_19",
      "CONVENTIONS.md_20"
    ],
    "name": "CONVENTIONS.md"
  }
}